{
    "1889b4752641149": {
        "description": "Класс охотник. Хорошая защита, неплохой урон. Плохая подвижность, но большой запас жизни.",
        "AllowSpells": [
            "global",
            4,
            5,
            6,
            7
        ],
        "stamina": 105,
        "protection": 0.6,
        "speed": 4,
        "radius": 50,
        "damageRate": 2.000000000000001,
        "intelligence": 0,
        "manaRegenAtRest": 0,
        "manaRegenAtCombat": 0,
        "spellDamagePower": 0,
        "maxEnergy": 150,
        "energyRegen": 16,
        "rotationEasing": 0.1,
        "level": 11,
        "xp": 860.9223804473877,
        "kills": 47,
        "nickname": "sdg",
        "class": "hunter"
    }
}